{
  "schema_version": 2,
  "id": "bot_plugin",
  "latest_version": "1.0.0",
  "etag": "\"2d0f10fe68ce94b07c300e2ffbc4d1f3d89f9a7ca030a09c6c54507b9976cee3\"",
  "releases": [
    {
      "url": "https://github.com/DancingSnow0517/Bot_Manager/releases/tag/1.0.0",
      "name": "Bot manager V1.0.0",
      "tag_name": "1.0.0",
      "created_at": "2022-01-09T04:09:01Z",
      "assets": [
        {
          "name": "BotPlugin-v1.0.0.mcdr",
          "size": 17657,
          "download_count": 31,
          "created_at": "2022-01-09T04:38:06Z",
          "browser_download_url": "https://github.com/DancingSnow0517/Bot_Manager/releases/download/1.0.0/BotPlugin-v1.0.0.mcdr"
        }
      ],
      "description": "",
      "prerelease": false,
      "parsed_version": "1.0.0"
    }
  ]
}